{"free":[],"sequences":[{"symbols":["cave_mid_v","cave_mid_v","cave_mid_v","cave_mid_v"],"layer":50,"block_size":[11,37],"location":{"kind":"absolute","pos":[273,419]},"max_width":1},{"symbols":["cave_mid_v","cave_mid_v","cave_mid_v","cave_mid_v"],"layer":50,"block_size":[11,37],"location":{"kind":"relative","pos":[111,-298]},"max_width":1},{"symbols":["cave_mid_v","cave_mid_v","cave_mid_v","cave_mid_v"],"layer":50,"block_size":[11,37],"location":{"kind":"relative","pos":[111,298]},"max_width":1},{"symbols":["cave_mid_v","cave_mid_v","cave_mid_v","cave_mid_v"],"layer":50,"block_size":[11,37],"location":{"kind":"relative","pos":[111,-298]},"max_width":1},{"symbols":["cave_mid_v","cave_mid_v","cave_mid_v","cave_mid_v"],"layer":50,"block_size":[11,37],"location":{"kind":"relative","pos":[111,298]},"max_width":1}]}